README.txt
setup.py
docs/HISTORY.txt
zopyx/__init__.py
zopyx.plone.migration.egg-info/PKG-INFO
zopyx.plone.migration.egg-info/SOURCES.txt
zopyx.plone.migration.egg-info/dependency_links.txt
zopyx.plone.migration.egg-info/entry_points.txt
zopyx.plone.migration.egg-info/namespace_packages.txt
zopyx.plone.migration.egg-info/not-zip-safe
zopyx.plone.migration.egg-info/requires.txt
zopyx.plone.migration.egg-info/top_level.txt
zopyx/plone/__init__.py
zopyx/plone/migration/__init__.py
zopyx/plone/migration/exporter.py
zopyx/plone/migration/importer.py
zopyx/plone/migration/read_content.py
zopyx/plone/migration/xx.py