Metadata-Version: 1.0
Name: zopyx.plone.migration
Version: 0.2.8
Summary: Export/import scripts for migration Plone 2+3 to Plone 4
Home-page: http://pypi.python.org/pypi/zopyx.plone.migration
Author: Andreas Jung
Author-email: info@zopyx.com
License: ZPL
Keywords: Zope Plone Migration
Platform: UNKNOWN
Classifier: Framework :: Plone
Classifier: Programming Language :: Python
